GuardiPy/__init__.py
GuardiPy/exceptions.py
GuardiPy/helpers.py
GuardiPy/CentraObject/__init__.py
GuardiPy/CentraObject/activity.py
GuardiPy/CentraObject/agent.py
GuardiPy/CentraObject/asset.py
GuardiPy/CentraObject/auxiliary_types.py
GuardiPy/CentraObject/event.py
GuardiPy/CentraObject/incident.py
GuardiPy/CentraObject/user.py
GuardiPy/CentraObject/vm.py
GuardiPy/CentraObject/Validation/__init__.py
GuardiPy/CentraObject/Validation/agent_schema.py
GuardiPy/CentraObject/Validation/auxiliary_schema.py
GuardiPy/CentraObject/Validation/event_schema.py
GuardiPy/CentraObject/Validation/incident_schema.py
GuardiPy-0.5.0.dist-info/LICENSE
GuardiPy-0.5.0.dist-info/METADATA
GuardiPy-0.5.0.dist-info/WHEEL
GuardiPy-0.5.0.dist-info/top_level.txt
GuardiPy-0.5.0.dist-info/RECORD
