Metadata-Version: 2.1
Name: GuardiPy
Version: 0.5.0
Summary: Unofficial Python 3.x library for Guardicore Centra (based on API 3.0).
Home-page: https://github.com/BlueBastion/GuardiPy
Author: cmcghee
Author-email: devops@idealintegrations.net
License: GPLv3
Platform: UNKNOWN
Classifier: Programming Language :: Python :: 3
Classifier: License :: OSI Approved :: GNU General Public License v3 (GPLv3)
Classifier: Operating System :: OS Independent
License-File: LICENSE
Requires-Dist: attrs (==20.3.0)
Requires-Dist: certifi (==2020.12.5)
Requires-Dist: chardet (==4.0.0)
Requires-Dist: idna (==2.10)
Requires-Dist: jsonschema (==3.2.0)
Requires-Dist: packaging (==20.9)
Requires-Dist: pep517 (==0.9.1)
Requires-Dist: pyparsing (==2.4.7)
Requires-Dist: pyrsistent (==0.17.3)
Requires-Dist: requests (==2.25.1)
Requires-Dist: six (==1.15.0)
Requires-Dist: toml (==0.10.2)
Requires-Dist: typed-ast (==1.4.2)
Requires-Dist: typing-extensions (==3.7.4.3)
Requires-Dist: urllib3 (==1.26.3)
